{"max_progr_len": 7, "src_ws": [], "vars": ["s(44)", "s(46)"], "init_progr_len": 7, "max_sk_sz": 5, "current_cost": 218, "user_instrs": [{"outpt_sk": ["s(44)"], "commutative": false, "inpt_sk": [64], "gas": 3, "disasm": "MLOAD", "opcode": "51", "id": "MLOAD_0"}, {"outpt_sk": ["s(46)"], "commutative": false, "inpt_sk": [17], "gas": 200, "disasm": "SLOAD", "opcode": "54", "id": "SLOAD_0"}], "tgt_ws": ["s(44)", 36990960606104792153599608932123900459733160954059643909152296882801502846976, "s(44)", 64, "s(46)"]}