{"max_progr_len": 40, "src_ws": ["s(0)", "s(1)", "s(2)"], "vars": ["s(0)", "s(1)", "s(2)", "s(22)", "s(25)", "s(26)", "s(35)", "s(36)", "s(37)", "s(40)"], "init_progr_len": 36, "max_sk_sz": 14, "current_cost": 874, "user_instrs": [{"outpt_sk": ["s(22)"], "commutative": true, "inpt_sk": ["s(2)", 1461501637330902918203684832716283019655932542975], "gas": 3, "disasm": "AND", "opcode": "16", "id": "AND_0"}, {"outpt_sk": ["s(25)"], "commutative": false, "inpt_sk": ["s(22)"], "gas": 700, "disasm": "EXTCODESIZE", "opcode": "3b", "id": "EXTCODESIZE_0"}, {"outpt_sk": ["s(35)"], "commutative": false, "inpt_sk": ["s(1)"], "gas": 3, "disasm": "MLOAD", "opcode": "51", "id": "MLOAD_0"}, {"outpt_sk": ["s(36)"], "commutative": true, "inpt_sk": ["s(37)", 36], "gas": 3, "disasm": "ADD", "opcode": "01", "id": "ADD_1"}, {"outpt_sk": ["s(37)"], "commutative": false, "inpt_sk": ["s(0)", "s(35)"], "gas": 3, "disasm": "SUB", "opcode": "03", "id": "SUB_0"}, {"outpt_sk": ["s(40)"], "commutative": true, "inpt_sk": ["s(0)", 36], "gas": 3, "disasm": "ADD", "opcode": "01", "id": "ADD_0"}, {"outpt_sk": ["s(26)"], "commutative": false, "inpt_sk": ["s(25)"], "gas": 3, "disasm": "ISZERO", "opcode": "15", "id": "ISZERO_0"}], "tgt_ws": ["s(26)", "s(26)", "s(22)", 0, "s(35)", "s(36)", "s(35)", 32, "s(40)", 1690723221, "s(22)", 0, 0, 0]}