{"max_progr_len": 12, "src_ws": ["s(0)", "s(1)", "s(2)"], "vars": ["s(0)", "s(1)", "s(10)", "s(11)", "s(12)", "s(13)", "s(14)", "s(2)"], "init_progr_len": 12, "max_sk_sz": 9, "current_cost": 33, "user_instrs": [{"outpt_sk": ["s(10)"], "commutative": true, "inpt_sk": [32, "s(11)"], "gas": 3, "disasm": "ADD", "opcode": "01", "id": "ADD_0"}, {"outpt_sk": ["s(13)"], "commutative": false, "inpt_sk": [], "gas": 2, "disasm": "ADDRESS", "opcode": "30", "id": "ADDRESS_0"}, {"outpt_sk": ["s(14)"], "commutative": true, "inpt_sk": [1461501637330902918203684832716283019655932542975, "s(2)"], "gas": 3, "disasm": "AND", "opcode": "16", "id": "AND_0"}, {"outpt_sk": ["s(11)"], "commutative": false, "inpt_sk": [64], "gas": 3, "disasm": "MLOAD", "opcode": "51", "id": "MLOAD_0"}, {"outpt_sk": ["s(12)"], "commutative": false, "inpt_sk": [], "gas": 2, "disasm": "CALLER", "opcode": "33", "id": "CALLER_0"}], "tgt_ws": ["s(10)", 0, "s(12)", "s(13)", 2111570644, "s(14)", "s(1)", "s(2)"]}