{"max_progr_len": 13, "src_ws": ["s(0)"], "vars": ["s(0)", "s(13)", "s(14)", "s(15)", "s(17)"], "init_progr_len": 13, "max_sk_sz": 5, "current_cost": 460, "user_instrs": [{"outpt_sk": ["s(17)"], "commutative": false, "inpt_sk": ["s(15)"], "gas": 200, "disasm": "SLOAD", "opcode": "54", "id": "SLOAD_1"}, {"outpt_sk": ["s(15)"], "commutative": true, "inpt_sk": ["s(13)", 2], "gas": 3, "disasm": "ADD", "opcode": "01", "id": "ADD_0"}, {"outpt_sk": ["s(13)"], "commutative": false, "inpt_sk": ["s(0)", 64], "gas": 30, "disasm": "SHA3", "opcode": "20", "id": "SHA3_0"}, {"outpt_sk": ["s(14)"], "commutative": false, "inpt_sk": ["s(13)"], "gas": 200, "disasm": "SLOAD", "opcode": "54", "id": "SLOAD_0"}], "tgt_ws": [7014, "s(14)", "s(17)", 2485]}