{"max_progr_len": 25, "src_ws": ["s(0)", "s(1)", "s(2)", "s(3)", "s(4)"], "vars": ["s(0)", "s(1)", "s(11)", "s(15)", "s(16)", "s(17)", "s(2)", "s(3)", "s(4)", "s(8)", "s(9)"], "init_progr_len": 25, "max_sk_sz": 11, "current_cost": 467, "user_instrs": [{"outpt_sk": ["s(17)"], "commutative": true, "inpt_sk": ["s(4)", "s(2)"], "gas": 3, "disasm": "ADD", "opcode": "01", "id": "ADD_3"}, {"outpt_sk": ["s(16)"], "commutative": false, "inpt_sk": ["s(15)"], "gas": 200, "disasm": "SLOAD", "opcode": "54", "id": "SLOAD_1"}, {"outpt_sk": ["s(15)"], "commutative": true, "inpt_sk": [2, "s(0)"], "gas": 3, "disasm": "ADD", "opcode": "01", "id": "ADD_2"}, {"outpt_sk": ["s(9)"], "commutative": true, "inpt_sk": ["s(11)", "s(2)"], "gas": 3, "disasm": "ADD", "opcode": "01", "id": "ADD_1"}, {"outpt_sk": ["s(8)"], "commutative": true, "inpt_sk": [1, "s(0)"], "gas": 3, "disasm": "ADD", "opcode": "01", "id": "ADD_0"}, {"outpt_sk": ["s(11)"], "commutative": false, "inpt_sk": ["s(8)"], "gas": 200, "disasm": "SLOAD", "opcode": "54", "id": "SLOAD_0"}], "tgt_ws": ["s(8)", "s(9)", "s(0)", "s(1)", "s(2)", "s(16)", "s(17)"]}