{"max_progr_len": 7, "src_ws": ["s(0)", "s(1)", "s(2)", "s(3)", "s(4)", "s(5)", "s(6)"], "vars": ["s(0)", "s(1)", "s(10)", "s(11)", "s(12)", "s(2)", "s(3)", "s(4)", "s(5)", "s(6)"], "init_progr_len": 5, "max_sk_sz": 10, "current_cost": 21, "user_instrs": [{"outpt_sk": ["s(11)"], "commutative": false, "inpt_sk": ["s(6)"], "gas": 3, "disasm": "MLOAD", "opcode": "51", "id": "MLOAD_0"}, {"outpt_sk": ["s(12)"], "commutative": false, "inpt_sk": ["s(11)"], "gas": 3, "disasm": "ISZERO", "opcode": "15", "id": "ISZERO_0"}], "tgt_ws": [3530, "s(12)", "s(10)", "s(0)", "s(1)", "s(2)", "s(3)", "s(4)", "s(5)", "s(6)"]}