{"max_progr_len": 4, "src_ws": ["s(0)", "s(1)", "s(2)", "s(3)", "s(4)", "s(5)", "s(6)", "s(7)", "s(8)"], "vars": ["s(0)", "s(1)", "s(11)", "s(2)", "s(3)", "s(4)", "s(5)", "s(6)", "s(7)", "s(8)"], "init_progr_len": 4, "max_sk_sz": 12, "current_cost": 12, "user_instrs": [{"outpt_sk": ["s(11)"], "commutative": false, "inpt_sk": ["s(3)"], "gas": 3, "disasm": "MLOAD", "opcode": "51", "id": "MLOAD_0"}], "tgt_ws": ["s(8)", "s(11)", "s(0)", "s(1)", "s(2)", "s(3)", "s(4)", "s(5)", "s(6)", "s(7)", "s(8)"]}