{"max_progr_len": 7, "src_ws": ["s(0)", "s(1)", "s(2)", "s(3)", "s(4)"], "vars": ["s(0)", "s(1)", "s(2)", "s(3)", "s(4)", "s(7)", "s(8)"], "init_progr_len": 7, "max_sk_sz": 9, "current_cost": 25, "user_instrs": [{"outpt_sk": ["s(8)"], "commutative": false, "inpt_sk": [1, "s(4)"], "gas": 5, "disasm": "SIGNEXTEND", "opcode": "0b", "id": "SIGNEXTEND_0"}, {"outpt_sk": ["s(7)"], "commutative": false, "inpt_sk": ["s(8)", 4], "gas": 5, "disasm": "DIV", "opcode": "04", "id": "DIV_0"}], "tgt_ws": [6606, "s(7)", "s(0)", "s(1)", "s(2)", "s(3)", "s(4)"]}