{"max_progr_len": 14, "src_ws": ["s(0)"], "vars": ["s(0)", "s(5)", "s(7)"], "init_progr_len": 11, "max_sk_sz": 5, "current_cost": 298, "user_instrs": [{"outpt_sk": ["s(7)"], "commutative": false, "inpt_sk": [4], "gas": 200, "disasm": "SLOAD", "opcode": "54", "id": "SLOAD_0"}, {"outpt_sk": ["s(5)"], "commutative": true, "inpt_sk": [1461501637330902918203684832716283019655932542975, "s(7)"], "gas": 3, "disasm": "AND", "opcode": "16", "id": "AND_0"}], "tgt_ws": [16339, "s(0)", "s(5)", 13137, "s(0)"]}