{"max_progr_len": 11, "src_ws": ["s(0)", "s(1)", "s(2)", "s(3)", "s(4)", "s(5)", "s(6)"], "vars": ["s(0)", "s(1)", "s(2)", "s(22)", "s(23)", "s(24)", "s(25)", "s(3)", "s(4)", "s(5)", "s(6)"], "init_progr_len": 11, "max_sk_sz": 11, "current_cost": 454, "user_instrs": [{"outpt_sk": ["s(22)"], "commutative": false, "inpt_sk": ["s(4)"], "gas": 3, "disasm": "MLOAD", "opcode": "51", "id": "MLOAD_0"}, {"outpt_sk": ["s(25)"], "commutative": false, "inpt_sk": ["s(24)"], "gas": 200, "disasm": "SLOAD", "opcode": "54", "id": "SLOAD_1"}, {"outpt_sk": ["s(23)"], "commutative": false, "inpt_sk": [16], "gas": 200, "disasm": "SLOAD", "opcode": "54", "id": "SLOAD_0"}, {"outpt_sk": ["s(24)"], "commutative": false, "inpt_sk": ["s(6)", "s(4)"], "gas": 30, "disasm": "SHA3", "opcode": "20", "id": "SHA3_0"}], "tgt_ws": ["s(22)", "s(1)", "s(23)", "s(25)", "s(22)", "s(2)", "s(3)", "s(4)", "s(5)", "s(0)"]}