{"max_progr_len": 34, "src_ws": ["s(0)", "s(1)", "s(2)", "s(3)", "s(4)"], "vars": ["s(0)", "s(1)", "s(17)", "s(18)", "s(2)", "s(22)", "s(23)", "s(24)", "s(25)", "s(26)", "s(3)", "s(4)"], "init_progr_len": 30, "max_sk_sz": 17, "current_cost": 158, "user_instrs": [{"outpt_sk": ["s(22)"], "commutative": false, "inpt_sk": [], "gas": 2, "disasm": "CALLDATASIZE", "opcode": "36", "id": "CALLDATASIZE_0"}, {"outpt_sk": ["s(23)"], "commutative": false, "inpt_sk": [68], "gas": 3, "disasm": "CALLDATALOAD", "opcode": "35", "id": "CALLDATALOAD_2"}, {"outpt_sk": ["s(17)"], "commutative": true, "inpt_sk": ["s(3)", "s(2)"], "gas": 3, "disasm": "ADD", "opcode": "01", "id": "ADD_1"}, {"outpt_sk": ["s(18)"], "commutative": true, "inpt_sk": [36, "s(0)"], "gas": 3, "disasm": "ADD", "opcode": "01", "id": "ADD_0"}, {"outpt_sk": ["s(26)"], "commutative": false, "inpt_sk": ["s(4)"], "gas": 3, "disasm": "CALLDATALOAD", "opcode": "35", "id": "CALLDATALOAD_1"}, {"outpt_sk": ["s(25)"], "commutative": true, "inpt_sk": ["s(26)", 1461501637330902918203684832716283019655932542975], "gas": 3, "disasm": "AND", "opcode": "16", "id": "AND_0"}, {"outpt_sk": ["s(24)"], "commutative": false, "inpt_sk": [36], "gas": 3, "disasm": "CALLDATALOAD", "opcode": "35", "id": "CALLDATALOAD_0"}], "tgt_ws": ["s(17)", "s(18)", "s(1)", "s(1)", "s(18)", "s(17)", "s(1)", "s(1)", "s(18)", "s(3)", 132, "s(4)", "s(22)", "s(23)", "s(24)", "s(25)", 683]}