{"max_progr_len": 24, "src_ws": ["s(0)", "s(1)", "s(2)"], "vars": ["s(0)", "s(1)", "s(2)", "s(24)", "s(25)", "s(27)"], "init_progr_len": 18, "max_sk_sz": 16, "current_cost": 188, "user_instrs": [{"outpt_sk": ["s(25)"], "commutative": true, "inpt_sk": [79228162514264337593543950336, "s(27)"], "gas": 5, "disasm": "MUL", "opcode": "02", "id": "MUL_0"}, {"outpt_sk": ["s(24)"], "commutative": false, "inpt_sk": [64], "gas": 3, "disasm": "MLOAD", "opcode": "51", "id": "MLOAD_0"}, {"outpt_sk": ["s(27)"], "commutative": true, "inpt_sk": [1461501637330902918203684832716283019655932542975, "s(2)"], "gas": 3, "disasm": "AND", "opcode": "16", "id": "AND_0"}], "tgt_ws": ["s(24)", "s(25)", 79228162514264337593543950336, "s(24)", "s(0)", 1461501637330902918203684832716283019655932542975, 0, 10, "s(0)", "s(2)", 12937, 0, "s(0)", "s(1)", "s(2)"]}