{"max_progr_len": 17, "src_ws": ["s(0)", "s(1)", "s(2)", "s(3)", "s(4)"], "vars": ["s(0)", "s(1)", "s(11)", "s(12)", "s(14)", "s(2)", "s(3)", "s(4)"], "init_progr_len": 13, "max_sk_sz": 12, "current_cost": 108, "user_instrs": [{"outpt_sk": ["s(14)"], "commutative": true, "inpt_sk": [1461501637330902918203684832716283019655932542975, "s(4)"], "gas": 3, "disasm": "AND", "opcode": "16", "id": "AND_1"}, {"outpt_sk": ["s(11)"], "commutative": false, "inpt_sk": [64], "gas": 3, "disasm": "MLOAD", "opcode": "51", "id": "MLOAD_0"}, {"outpt_sk": ["s(12)"], "commutative": true, "inpt_sk": ["s(2)", 18446744073709551615], "gas": 3, "disasm": "AND", "opcode": "16", "id": "AND_0"}], "tgt_ws": ["s(11)", "s(12)", "s(3)", "s(11)", 21168643812248659736475371190363486315673762353297546972841113673135497128628, "s(14)", "s(0)", "s(1)", "s(2)", "s(3)", "s(4)"]}